README.md
setup.py
ritassist/__init__.py
ritassist/address.py
ritassist/api.py
ritassist/authentication.py
ritassist/device.py
ritassist/json_utils.py
ritassist/trip.py
ritassist/tripdetail.py
ritassist.egg-info/PKG-INFO
ritassist.egg-info/SOURCES.txt
ritassist.egg-info/dependency_links.txt
ritassist.egg-info/not-zip-safe
ritassist.egg-info/requires.txt
ritassist.egg-info/top_level.txt